test/__init__.py
test/main.py
test/rq_push_job.py
test/sample_plugin.py
vais_plugin/__init__.py
vais_plugin/plugin_config.py
vais_plugin/plugin_skeleton.py
vais_plug-0.2.7.dist-info/METADATA
vais_plug-0.2.7.dist-info/WHEEL
vais_plug-0.2.7.dist-info/top_level.txt
vais_plug-0.2.7.dist-info/RECORD
