Metadata-Version: 2.1
Name: vais-plug
Version: 0.2.7
Summary: Skeleton Plugin for VAIS analytic system
Home-page: https://gitlab.com/vais/product/analytic/skeleton-plugin-lib
Author: Binh Nguyen
Author-email: binhnguyen@vais.vn
License: MIT
Platform: UNKNOWN
Classifier: License :: OSI Approved :: MIT License
Classifier: Programming Language :: Python :: 3
Classifier: Programming Language :: Python :: 3.7
Requires-Dist: rq (==1.9.0)
Requires-Dist: requests (==2.23.0)
Requires-Dist: redis (==3.5.0)
Requires-Dist: prometheus-client (==0.7.1)
Requires-Dist: flask (==1.1.1)
Requires-Dist: apscheduler (==3.6.3)
Requires-Dist: pyyaml (==5.3)
